pynewmarkdisp/__init__.py
pynewmarkdisp/empir_corr.py
pynewmarkdisp/infslope.py
pynewmarkdisp/newmark.py
pynewmarkdisp/spatial.py
pynewmarkdisp-0.1.0.dist-info/LICENSE
pynewmarkdisp-0.1.0.dist-info/WHEEL
pynewmarkdisp-0.1.0.dist-info/METADATA
pynewmarkdisp-0.1.0.dist-info/RECORD
