Metadata-Version: 2.1
Name: pynewmarkdisp
Version: 0.1.0
Summary: Calculation of permanent displacements in slopes by the Newmark's method
Author: Silvana Montoya-Noguera, Fernando Lopez-Caballero
Author-email: "Exneyder A. Montoya-Araque" <eamontoyaa@gmail.com>
Requires-Python: >=3.9
Classifier: License :: OSI Approved :: MIT License
Requires-Dist: numpy >=1.22.4
Requires-Dist: matplotlib >=3.7.1
Requires-Dist: scipy >= 1.9.0
Requires-Dist: numba >=0.56.4
Project-URL: Documentation, https://eamontoyaa.github.io/pyNewmarkDisp/
Project-URL: Source, https://github.com/eamontoyaa/pynewmarkdisp
